aiospb/__init__.py
aiospb/bootstrap.py
aiospb/hosts/__init__.py
aiospb/hosts/commands.py
aiospb/hosts/hosts.py
aiospb/hosts/values.py
aiospb/infra/encoding/__init__.py
aiospb/infra/encoding/json.py
aiospb/infra/encoding/protobuf/__init__.py
aiospb/infra/encoding/protobuf/core.py
aiospb/infra/encoding/protobuf/sparkplug.proto
aiospb/infra/encoding/protobuf/sparkplug_pb2.py
aiospb/infra/encoding/protobuf/sparkplug_pb2.pyi
aiospb/infra/fs.py
aiospb/infra/inmem.py
aiospb/infra/paho.py
aiospb/infra/stores.py
aiospb/messages/__init__.py
aiospb/messages/hosts.py
aiospb/messages/nodes.py
aiospb/messages/ports.py
aiospb/messages/values.py
aiospb/mqtt/core.py
aiospb/nodes/__init__.py
aiospb/nodes/devices.py
aiospb/nodes/messages.py
aiospb/nodes/nodes.py
aiospb/nodes/ports.py
aiospb/nodes/scanning.py
aiospb/nodes/values.py
aiospb/shared.py
aiospb-8.0.12.dist-info/METADATA
aiospb-8.0.12.dist-info/WHEEL
aiospb-8.0.12.dist-info/RECORD
