Metadata-Version: 2.4
Name: aiospb
Version: 8.0.12
Summary: Library to comunicate with MQTT following Sparkplug B estandard
License: LGPL
Author: Salvador Ruiz
Author-email: sruiz@gruposavia.eu
Requires-Python: >=3.12,<4.0
Classifier: License :: Other/Proprietary License
Classifier: Programming Language :: Python :: 3
Classifier: Programming Language :: Python :: 3.12
Classifier: Programming Language :: Python :: 3.13
Classifier: Programming Language :: Python :: 3.14
Requires-Dist: aiofiles (>=24.1.0,<25.0.0)
Requires-Dist: aiomqtt (>=2.0.0,<3.0.0)
Requires-Dist: protobuf (>=5.28.0,<6.0.0)
